kailin/__init__.py
kailin/kl_settings.py
kailin/R_processing/__init__.py
kailin/kl_sample/__init__.py
kailin/kl_sample/paper_sample.py
kailin/omic_functions/CellColorMapPlot.py
kailin/omic_functions/CellColorMapPlot2.py
kailin/omic_functions/Download.py
kailin/omic_functions/__init__.py
kailin/omic_functions/clone_analysis.py
kailin/omic_functions/datasets.py
kailin/omic_functions/hf.py
kailin/omic_functions/logging.py
kailin/omic_functions/matrix.py
kailin/omic_functions/pl.py
kailin/omic_functions/pp.py
kailin/omic_functions/settings.py
kailin/omic_functions/simulate.py
kailin/omic_functions/tl.py
kailin/omic_functions/help_functions/__init__.py
kailin/omic_functions/help_functions/_docs.py
kailin/omic_functions/help_functions/_help_functions_CoSpar.py
kailin/omic_functions/plotting/__init__.py
kailin/omic_functions/plotting/_clone.py
kailin/omic_functions/plotting/_gene.py
kailin/omic_functions/plotting/_map.py
kailin/omic_functions/plotting/_utils.py
kailin/omic_functions/preprocessing/__init__.py
kailin/omic_functions/preprocessing/_preprocessing.py
kailin/omic_functions/tmap/__init__.py
kailin/omic_functions/tmap/_tmap_core.py
kailin/omic_functions/tmap/_utils.py
kailin/omic_functions/tmap/map_reconstruction.py
kailin/omic_functions/tmap/optimal_transport.py
kailin/omic_functions/tool/__init__.py
kailin/omic_functions/tool/_clone.py
kailin/omic_functions/tool/_gene.py
kailin/omic_functions/tool/_map.py
kailin/omic_functions/tool/_utils.py
kailin/preprocessing/__init__.py
kailin/preprocessing/kl_pre.py
kailin/preprocessing/kl_similar_matrix.py
kailin/workcatalogue/__init__.py
kailin/workcatalogue/kl_load.py
kailin-0.2.2.5.dist-info/METADATA
kailin-0.2.2.5.dist-info/WHEEL
kailin-0.2.2.5.dist-info/top_level.txt
kailin-0.2.2.5.dist-info/RECORD
