Metadata-Version: 2.1
Name: kailin
Version: 0.2.2.5
Summary: KAILINss - TOGGLE(KAILIN): Single Cell Fate Tracing tools
Home-page: https://github.com/FullBlackWolf/KAILINss
Author: Junpeng Chen(Donald Louis)
Author-email: drchenjunpeng@hotmail.com
License: MIT
Classifier: License :: OSI Approved :: MIT License
Classifier: Programming Language :: Python
Classifier: Programming Language :: Python :: 3
Classifier: Programming Language :: Python :: 3.9
Classifier: Programming Language :: Python :: Implementation :: CPython
Classifier: Programming Language :: Python :: Implementation :: PyPy
Requires-Python: >=3.9, <3.10
Requires-Dist: anndata ==0.10.6
Requires-Dist: anyio ==4.3.0
Requires-Dist: argon2-cffi ==23.1.0
Requires-Dist: argon2-cffi-bindings ==21.2.0
Requires-Dist: array-api-compat ==1.4.1
Requires-Dist: arrow ==1.3.0
Requires-Dist: asttokens ==2.4.1
Requires-Dist: async-lru ==2.0.4
Requires-Dist: attrs ==23.2.0
Requires-Dist: Babel ==2.14.0
Requires-Dist: backports.tarfile ==1.2.0
Requires-Dist: beautifulsoup4 ==4.12.3
Requires-Dist: bleach ==6.1.0
Requires-Dist: certifi ==2024.2.2
Requires-Dist: cffi ==1.16.0
Requires-Dist: charset-normalizer ==3.3.2
Requires-Dist: colorama ==0.4.6
Requires-Dist: comm ==0.2.2
Requires-Dist: contourpy ==1.2.0
Requires-Dist: cospar ==0.3.3
Requires-Dist: cycler ==0.12.1
Requires-Dist: debugpy ==1.8.1
Requires-Dist: decorator ==5.1.1
Requires-Dist: defusedxml ==0.7.1
Requires-Dist: docutils ==0.21.2
Requires-Dist: et-xmlfile ==2.0.0
Requires-Dist: ete3 ==3.1.3
Requires-Dist: exceptiongroup ==1.2.0
Requires-Dist: executing ==2.0.1
Requires-Dist: fastcluster ==1.2.6
Requires-Dist: fastjsonschema ==2.19.1
Requires-Dist: fonttools ==4.49.0
Requires-Dist: fqdn ==1.5.1
Requires-Dist: frozendict ==2.4.4
Requires-Dist: get-annotations ==0.1.2
Requires-Dist: gseapy ==1.1.2
Requires-Dist: h11 ==0.14.0
Requires-Dist: h5py ==3.10.0
Requires-Dist: html5lib ==1.1
Requires-Dist: httpcore ==1.0.4
Requires-Dist: httpx ==0.27.0
Requires-Dist: idna ==3.6
Requires-Dist: igraph ==0.11.4
Requires-Dist: importlib-metadata ==6.8.0
Requires-Dist: importlib-resources ==6.3.0
Requires-Dist: ipykernel ==6.29.3
Requires-Dist: ipython ==8.18.1
Requires-Dist: ipywidgets ==8.1.2
Requires-Dist: isoduration ==20.11.0
Requires-Dist: jaraco.classes ==3.4.0
Requires-Dist: jaraco.context ==5.3.0
Requires-Dist: jaraco.functools ==4.0.1
Requires-Dist: jedi ==0.19.1
Requires-Dist: Jinja2 ==3.1.3
Requires-Dist: joblib ==1.3.2
Requires-Dist: json5 ==0.9.22
Requires-Dist: jsonpointer ==2.4
Requires-Dist: jsonschema ==4.21.1
Requires-Dist: jsonschema-specifications ==2023.12.1
Requires-Dist: jupyter ==1.0.0
Requires-Dist: jupyter-client ==8.6.1
Requires-Dist: jupyter-console ==6.6.3
Requires-Dist: jupyter-core ==5.7.2
Requires-Dist: jupyter-events ==0.9.1
Requires-Dist: jupyter-lsp ==2.2.4
Requires-Dist: jupyter-server ==2.13.0
Requires-Dist: jupyter-server-terminals ==0.5.3
Requires-Dist: jupyterlab ==4.1.4
Requires-Dist: jupyterlab-pygments ==0.3.0
Requires-Dist: jupyterlab-server ==2.25.4
Requires-Dist: jupyterlab-widgets ==3.0.10
Requires-Dist: keyring ==25.2.1
Requires-Dist: kiwisolver ==1.4.5
Requires-Dist: lab ==8.1
Requires-Dist: leidenalg ==0.10.2
Requires-Dist: llvmlite ==0.42.0
Requires-Dist: lxml ==5.2.2
Requires-Dist: markdown-it-py ==3.0.0
Requires-Dist: MarkupSafe ==2.1.5
Requires-Dist: matplotlib ==3.7.5
Requires-Dist: matplotlib-inline ==0.1.6
Requires-Dist: mdurl ==0.1.2
Requires-Dist: mistune ==3.0.1
Requires-Dist: mizani ==0.11.0
Requires-Dist: more-itertools ==10.2.0
Requires-Dist: multitasking ==0.0.11
Requires-Dist: natsort ==8.4.0
Requires-Dist: nbclient ==0.10.0
Requires-Dist: nbconvert ==7.8.0
Requires-Dist: nbformat ==5.10.2
Requires-Dist: nest-asyncio ==1.6.0
Requires-Dist: networkx ==3.2.1
Requires-Dist: nh3 ==0.2.17
Requires-Dist: notebook ==7.1.1
Requires-Dist: notebook-shim ==0.2.4
Requires-Dist: numba ==0.59.0
Requires-Dist: numpy ==1.26.4
Requires-Dist: openpyxl ==3.1.5
Requires-Dist: overrides ==7.7.0
Requires-Dist: packaging ==24.0
Requires-Dist: pandas ==2.2.2
Requires-Dist: pandocfilters ==1.5.1
Requires-Dist: parso ==0.8.3
Requires-Dist: patsy ==0.5.6
Requires-Dist: peewee ==3.17.5
Requires-Dist: pillow ==10.2.0
Requires-Dist: pip ==24.2
Requires-Dist: pkginfo ==1.11.0
Requires-Dist: platformdirs ==4.2.0
Requires-Dist: plotnine ==0.13.1
Requires-Dist: prometheus-client ==0.20.0
Requires-Dist: prompt-toolkit ==3.0.43
Requires-Dist: psutil ==5.9.8
Requires-Dist: pure-eval ==0.2.2
Requires-Dist: pycparser ==2.21
Requires-Dist: pygame ==2.5.2
Requires-Dist: Pygments ==2.17.2
Requires-Dist: pynndescent ==0.5.11
Requires-Dist: pyparsing ==3.1.2
Requires-Dist: python-dateutil ==2.9.0.post0
Requires-Dist: python-json-logger ==2.0.7
Requires-Dist: pytz ==2024.1
Requires-Dist: pywin32 ==306
Requires-Dist: pywin32-ctypes ==0.2.2
Requires-Dist: pywinpty ==2.0.13
Requires-Dist: PyYAML ==6.0.1
Requires-Dist: pyzmq ==25.1.2
Requires-Dist: qtconsole ==5.5.1
Requires-Dist: QtPy ==2.4.1
Requires-Dist: readme-renderer ==43.0
Requires-Dist: referencing ==0.33.0
Requires-Dist: requests ==2.31.0
Requires-Dist: requests-toolbelt ==1.0.0
Requires-Dist: rfc3339-validator ==0.1.4
Requires-Dist: rfc3986 ==2.0.0
Requires-Dist: rfc3986-validator ==0.1.1
Requires-Dist: rich ==13.7.1
Requires-Dist: rpds-py ==0.18.0
Requires-Dist: scanpy ==1.9.8
Requires-Dist: scikit-learn ==1.4.1.post1
Requires-Dist: scikit-misc ==0.3.1
Requires-Dist: scipy ==1.12.0
Requires-Dist: seaborn ==0.13.2
Requires-Dist: Send2Trash ==1.8.2
Requires-Dist: session-info ==1.0.0
Requires-Dist: setuptools ==68.2.2
Requires-Dist: simplejson ==3.19.2
Requires-Dist: six ==1.16.0
Requires-Dist: sniffio ==1.3.1
Requires-Dist: soupsieve ==2.5
Requires-Dist: stack-data ==0.6.3
Requires-Dist: statsmodels ==0.14.1
Requires-Dist: stdlib-list ==0.10.0
Requires-Dist: terminado ==0.18.1
Requires-Dist: texttable ==1.7.0
Requires-Dist: threadpoolctl ==3.3.0
Requires-Dist: tinycss2 ==1.2.1
Requires-Dist: tomli ==2.0.1
Requires-Dist: tornado ==6.4
Requires-Dist: tqdm ==4.66.2
Requires-Dist: traitlets ==5.14.2
Requires-Dist: twine ==5.1.0
Requires-Dist: txt2tags ==3.9
Requires-Dist: types-python-dateutil ==2.8.19.20240311
Requires-Dist: typing-extensions ==4.10.0
Requires-Dist: tzdata ==2024.1
Requires-Dist: umap-learn ==0.5.5
Requires-Dist: uri-template ==1.3.0
Requires-Dist: urllib3 ==2.2.1
Requires-Dist: wcwidth ==0.2.13
Requires-Dist: webcolors ==1.13
Requires-Dist: webencodings ==0.5.1
Requires-Dist: websocket-client ==1.7.0
Requires-Dist: wheel ==0.41.2
Requires-Dist: widgetsnbextension ==4.0.10
Requires-Dist: yfinance ==0.2.40
Requires-Dist: zipp ==3.18.0
